{
  "overall_status": "down",
  "uptime_30d": 88.08,
  "components": [
    {
      "name": "API",
      "icon": {
        "type": {
          "displayName": "Zap"
        },
        "key": null,
        "ref": null,
        "props": {
          "size": 16,
          "strokeWidth": 1.75
        }
      },
      "status": "down",
      "latency_ms": 0,
      "description": "HookSniff REST API (Cloud Run)",
      "last_checked": "2026-05-31T21:07:49.574Z"
    },
    {
      "name": "Dashboard",
      "icon": {
        "type": {
          "displayName": "Monitor"
        },
        "key": null,
        "ref": null,
        "props": {
          "size": 16,
          "strokeWidth": 1.75
        }
      },
      "status": "degraded",
      "latency_ms": 0,
      "description": "Next.js frontend (Vercel)",
      "last_checked": "2026-05-31T21:07:49.574Z"
    },
    {
      "name": "Worker",
      "icon": {
        "type": {
          "displayName": "Settings"
        },
        "key": null,
        "ref": null,
        "props": {
          "size": 16,
          "strokeWidth": 1.75
        }
      },
      "status": "unknown",
      "latency_ms": null,
      "description": "Background delivery worker (Cloud Run)",
      "last_checked": "2026-05-31T21:07:49.574Z"
    },
    {
      "name": "Database",
      "icon": {
        "type": {
          "displayName": "Database"
        },
        "key": null,
        "ref": null,
        "props": {
          "size": 16,
          "strokeWidth": 1.75
        }
      },
      "status": "down",
      "latency_ms": 0,
      "description": "PostgreSQL (Neon)",
      "last_checked": "2026-05-31T21:07:49.574Z"
    },
    {
      "name": "Cache",
      "icon": {
        "type": {
          "displayName": "HardDrive"
        },
        "key": null,
        "ref": null,
        "props": {
          "size": 16,
          "strokeWidth": 1.75
        }
      },
      "status": "unknown",
      "latency_ms": 0,
      "description": "Redis (Upstash)",
      "last_checked": "2026-05-31T21:07:49.574Z"
    },
    {
      "name": "Email Service",
      "icon": {
        "type": {
          "displayName": "Mail"
        },
        "key": null,
        "ref": null,
        "props": {
          "size": 16,
          "strokeWidth": 1.75
        }
      },
      "status": "healthy",
      "latency_ms": 332,
      "description": "Gmail API",
      "last_checked": "2026-05-31T21:07:49.574Z"
    },
    {
      "name": "Storage",
      "icon": {
        "type": {
          "displayName": "Cloud"
        },
        "key": null,
        "ref": null,
        "props": {
          "size": 16,
          "strokeWidth": 1.75
        }
      },
      "status": "healthy",
      "latency_ms": 46,
      "description": "Cloudflare R2",
      "last_checked": "2026-05-31T21:07:49.574Z"
    }
  ],
  "checked_at": "2026-05-31T21:07:49.574Z",
  "response_times": {
    "Email Service": [
      286,
      285,
      332
    ],
    "Storage": [
      48,
      40,
      46
    ]
  }
}